droplo/__init__.py
droplo/api.py
droplo/cache.py
droplo/connection.py
droplo/exceptions.py
droplo/resource.py
droplo-0.1.3.dist-info/METADATA
droplo-0.1.3.dist-info/RECORD
droplo-0.1.3.dist-info/WHEEL
droplo-0.1.3.dist-info/top_level.txt
tests/__init__.py
tests/test_api.py
tests/test_cache.py
