Metadata-Version: 2.1
Name: droplo
Version: 0.1.3
Summary: Official Python SDK for the Droplo content API
Home-page: https://github.com/droploio/droplo.py
Author: Droplo Inc
Author-email: contact@droplo.io
License: UNKNOWN
Platform: UNKNOWN
Classifier: Development Status :: 2 - Pre-Alpha
Classifier: Programming Language :: Python
Classifier: Programming Language :: Python :: 2
Classifier: Programming Language :: Python :: 2.7
Classifier: Programming Language :: Python :: 3
Classifier: Programming Language :: Python :: 3.4
Classifier: Programming Language :: Python :: 3.5
Requires-Dist: requests (>=2.14.0)
